Metadata-Version: 2.1
Name: pyofs
Version: 0.2
Summary: uses <open>
Home-page: UNKNOWN
Author-email: ivan.selyakovich@gmail.com
License: UNKNOWN
Platform: UNKNOWN
